{
    "utilidades":[
        "!ajuda", "!help", "!menu", ".help", ".menu",
        "!s",
        "!sgif",
        "!sgif2",
        "!ssf",
        "!simg",
        "!audio",
        "!tps",
        "!traduz",
        "!voz",
        "!img",
        "!noticias",
        "!rastreio",
        "!calc",
        "!info",
        "!google",
        "!moeda",
        "!clima",
        "!ddd",
        "!play",
        "!yt",
        "!anime",
        "!animelanc",
        "!meusdados",
        "!reportar"
    ],
    "admin_grupo":[
        "!status",
        "!regras",
        "!add",
        "!ban",
        "!promover",
        "!rebaixar",
        "!mt",
        "!adms",
        "!dono",
        "!link",
        "!rlink",
        "!f",
        "!alink",
        "!bv",
        "!afake",
        "!aflood",
        "!apg",
        "!bantodos",
        "!vb",
        "!votar",
        "!topativos",
        "!destravar",
        "!contador", 
        "!atividade",
        "!alterarcont",
        "!imarcar",
        "!ibanir",
        "!votacao",
        "!enquete",
        "!votarenquete",
        "!verenquete",
        "!bcmd",
        "!dcmd"
    ],
    "diversao":[
        "!mascote",
        "!viadometro",
        "!detector",
        "!massacote",
        "!roletarussa",
        "!casal",
        "!gadometro",
        "!bafometro",
        "!top5",
        "!par",
        "!roletrando",
        "!malacos", 
        "!fch"
    ],
    "dono_bot":[
        "!sair",
        "!sairgrupos",
        "!vervips",
        "!infocompleta",
        "!floodgrupo",
        "!entrargrupo",
        "!bc",
        "!bcgrupos",
        "!print",
        "!limpartudo",
        "!limpar",
        "!listablock",
        "!bloquear",
        "!limitediario",
        "!taxalimite",
        "!limitarmsgs",
        "!desbloquear",
        "!estado",
        "!admin",
        "!rconfig",
        "!mudarlimite",
        "!tipo",
        "!limparvip",
        "!rtodos",
        "!r",
        "!verdados",
        "!desligar"
    ],
    "excecoes_contagem": [
        "!meusdados",
        "!ajuda","!help", "!menu", ".help", ".menu",
        "!info",
        "!reportar",
        "!status",
        "!regras",
        "!add",
        "!ban",
        "!promover",
        "!rebaixar",
        "!mt",
        "!adms",
        "!dono",
        "!link",
        "!rlink",
        "!f",
        "!alink",
        "!bv",
        "!afake",
        "!aflood",
        "!apg",
        "!bantodos",
        "!vb",
        "!votar",
        "!topativos",
        "!destravar",
        "!contador",
        "!alterarcont",
        "!atividade",
        "!imarcar",
        "!ibanir",
        "!votacao",
        "!enquete",
        "!votarenquete",
        "!verenquete",
        "!bcmd",
        "!dcmd"
    ]
}